facebook_ads_reports/__init__.py
facebook_ads_reports/client.py
facebook_ads_reports/exceptions.py
facebook_ads_reports/models.py
facebook_ads_reports/py.typed
facebook_ads_reports/retry.py
facebook_ads_reports/utils.py
facebook_ads_reports-2.0.1.dist-info/LICENSE
facebook_ads_reports-2.0.1.dist-info/METADATA
facebook_ads_reports-2.0.1.dist-info/WHEEL
facebook_ads_reports-2.0.1.dist-info/RECORD
