Metadata-Version: 2.3
Name: facebook-ads-reports
Version: 2.0.1
Summary: ETL module for Facebook Ads API v23 with lightweight native Python data processing
License: GPL
Keywords: facebook-ads,etl,data-extraction,reports,flatten-json
Author: Joao Brito
Requires-Python: >=3.11,<3.15
Classifier: Development Status :: 5 - Production/Stable
Classifier: Intended Audience :: Developers
Classifier: Intended Audience :: Information Technology
Classifier: License :: OSI Approved :: GNU General Public License v3 (GPLv3)
Classifier: Operating System :: OS Independent
Classifier: Programming Language :: Python :: 3
Classifier: Programming Language :: Python :: 3.11
Classifier: Programming Language :: Python :: 3.12
Classifier: Programming Language :: Python :: 3.13
Classifier: Programming Language :: Python :: 3.14
Classifier: Topic :: Software Development :: Libraries :: Python Modules
Classifier: Topic :: Internet :: WWW/HTTP :: Dynamic Content
Classifier: Typing :: Typed
Provides-Extra: dev
Requires-Dist: mypy (>=1.0.0) ; extra == "dev"
Requires-Dist: pytest (>=8.0.0) ; extra == "dev"
Requires-Dist: python-dotenv (>=1.1.1,<2.0.0)
Requires-Dist: requests (>=2.32.4,<3.0.0)
Project-URL: Homepage, https://github.com/machado000/facebook-ads-reports
Project-URL: Issues, https://github.com/machado000/facebook-ads-reports/issues
